LICENSE.txt
MANIFEST.in
NOTICE
README.md
setup.py
ade/__init__.py
ade/abort.py
ade/args.py
ade/de.py
ade/history.py
ade/image.py
ade/individual.py
ade/population.py
ade/report.py
ade/util.py
ade.egg-info/PKG-INFO
ade.egg-info/SOURCES.txt
ade.egg-info/dependency_links.txt
ade.egg-info/entry_points.txt
ade.egg-info/requires.txt
ade.egg-info/top_level.txt
ade.egg-info/zip-safe
ade/examples/__init__.py
ade/examples/covid19.py
ade/examples/data.py
ade/examples/goldstein-price.c
ade/examples/goldstein-price.py
ade/examples/thermistor.py
ade/examples/voc.py
ade/scripts/__init__.py
ade/scripts/examples.py
ade/scripts/lgg.py
ade/scripts/pv.py
ade/scripts/viewer.py
ade/test/__init__.py
ade/test/test_de.py
ade/test/test_history.py
ade/test/test_individual.py
ade/test/test_population.py
ade/test/test_report.py
ade/test/testbase.py