Metadata-Version: 2.1
Name: ade
Version: 1.3.3
Summary:  Asynchronous Differential Evolution, with efficient multiprocessing. 
Home-page: http://edsuom.com/ade.html
Author: Edwin A. Suominen
Author-email: foss@edsuom.com
Maintainer: Edwin A. Suominen
Maintainer-email: foss@edsuom.com
License: Apache License (2.0)
Project-URL: API, http://edsuom.com/ade/ade.html
Project-URL: GitHub, https://github.com/edsuom/ade
Keywords: Twisted,asynchronous,differential evolution,de,genetic algorithm,evolution
Platform: OS Independent
Classifier: Development Status :: 5 - Production/Stable
Classifier: Intended Audience :: Developers
Classifier: Intended Audience :: Science/Research
Classifier: License :: OSI Approved :: Apache Software License
Classifier: Operating System :: OS Independent
Classifier: Programming Language :: Python
Classifier: Framework :: Twisted
Classifier: Topic :: Software Development :: Libraries :: Python Modules
Classifier: Topic :: Scientific/Engineering :: Mathematics
Classifier: Topic :: Scientific/Engineering :: Artificial Intelligence
